{
	"configurations" : 
	[
		{
			"directories" : 
			[
				{
					"build" : ".",
					"hasInstallRule" : true,
					"jsonFile" : "directory-.-022e04cb2d5950c75d6c.json",
					"minimumCMakeVersion" : 
					{
						"string" : "3.12"
					},
					"projectIndex" : 0,
					"source" : ".",
					"targetIndexes" : 
					[
						0,
						1
					]
				}
			],
			"name" : "",
			"projects" : 
			[
				{
					"directoryIndexes" : 
					[
						0
					],
					"name" : "cpp_pubsub",
					"targetIndexes" : 
					[
						0,
						1
					]
				}
			],
			"targets" : 
			[
				{
					"directoryIndex" : 0,
					"id" : "cpp_pubsub_uninstall::@6890427a1f51a3e7e1df",
					"jsonFile" : "target-cpp_pubsub_uninstall-0bcfc8ea3185628fe5ca.json",
					"name" : "cpp_pubsub_uninstall",
					"projectIndex" : 0
				},
				{
					"directoryIndex" : 0,
					"id" : "uninstall::@6890427a1f51a3e7e1df",
					"jsonFile" : "target-uninstall-030fb5aa61b15f328df1.json",
					"name" : "uninstall",
					"projectIndex" : 0
				}
			]
		}
	],
	"kind" : "codemodel",
	"paths" : 
	{
		"build" : "/home/devuser/Workspaces/build/cpp_pubsub",
		"source" : "/home/devuser/Workspaces/ros2learn_ws/src/cpp_pubsub"
	},
	"version" : 
	{
		"major" : 2,
		"minor" : 3
	}
}
